prompits/Agent.py
prompits/AgentAddress.py
prompits/LogEvent.py
prompits/Message.py
prompits/Pathfinder.py
prompits/Pathway.py
prompits/Pioneer.py
prompits/Pit.py
prompits/Plaza.py
prompits/Plug.py
prompits/Pool.py
prompits/Practice.py
prompits/Profiler.py
prompits/Schema.py
prompits/__init__.py
prompits/evaluators/NumericDifference.py
prompits/evaluators/PathwayEvaluator.py
prompits/evaluators/StringSimilarity.py
prompits/messages/StatusMessage.py
prompits/messages/UsePracticeMessage.py
prompits/messages/__init__.py
prompits/pits/__init__.py
prompits/plazas/AgentPlaza.py
prompits/plazas/MessagePlaza.py
prompits/plazas/__init__.py
prompits/plugs/HTTPPlug.py
prompits/plugs/TCPPlug.py
prompits/plugs/__init__.py
prompits/plugs/gRPCPlug-bak.py
prompits/plugs/gRPCPlug.py
prompits/plugs/protos/__init__.py
prompits/plugs/protos/agent.proto
prompits/plugs/protos/agent_pb2.py
prompits/plugs/protos/agent_pb2_grpc.py
prompits/pools/DatabasePool.py
prompits/pools/PostgresPool.py
prompits/pools/SQLitePool.py
prompits/pools/__init__.py
prompits/schemas/Pathway.schema.json
prompits/services/APIService.py
prompits/services/Job.py
prompits/services/JobMarket.py
prompits/services/JobResult.py
prompits/services/LLM.py
prompits/services/MCPClient.py
prompits/services/Ollama.py
prompits/services/Pouch.py
prompits/services/Service.py
prompits/services/__init__.py
prompits-0.0.2.dist-info/METADATA
prompits-0.0.2.dist-info/WHEEL
prompits-0.0.2.dist-info/RECORD
